podder_lib/__init__.py
podder_lib/data_sources/__init__.py
podder_lib/data_sources/base_data_source.py
podder_lib/data_sources/gcs_data_source.py
podder_lib/data_sources/local_data_source.py
podder_lib/db_connectors/__init__.py
podder_lib/db_connectors/mssql_connector.py
podder_lib/formatters/__init__.py
podder_lib/formatters/currency_formatter.py
podder_lib/formatters/phone_number_formatter.py
podder_lib/sensors/__init__.py
podder_lib/sensors/services/__init__.py
podder_lib/sensors/services/data_source_service.py
podder_lib/sensors/services/database_service.py
podder_lib/sensors/services/input_validator_service.py
podder_lib/sensors/services/new_file_key_service.py
podder_lib/validators/__init__.py
podder_lib/validators/data_validator.py
podder_lib/validators/image_validator.py
podder_lib/writers/__init__.py
podder_lib/writers/services/__init__.py
podder_lib/writers/services/data_source_service.py
podder_lib/writers/services/database_service.py
podder_lib/writers/services/input_validator_service.py
podder_lib-0.1.5.dist-info/METADATA
podder_lib-0.1.5.dist-info/WHEEL
podder_lib-0.1.5.dist-info/top_level.txt
podder_lib-0.1.5.dist-info/RECORD
