Metadata-Version: 2.1
Name: podder-lib
Version: 0.1.5
Summary: Library for the Podder Task.
Home-page: https://github.com/podder-ai/podder-lib
Author: podder-ai
Author-email: UNKNOWN
License: UNKNOWN
Platform: UNKNOWN
Requires-Dist: pytest (==4.3.1)
Requires-Dist: pytest-cov (==2.6.1)
Requires-Dist: SQLAlchemy (==1.3.3)
Requires-Dist: Pillow (==5.4.1)
Requires-Dist: pyodbc (==4.0.26)
Requires-Dist: podder-task-base (<0.9.0,>=0.8.0)
Requires-Dist: google-cloud-storage (==1.13.2)
